Workbook

Sheet Register
A1: Radiology Room E.D. Vol B - Submittal Register
A2: Yellow cells are inputs. Required Approval = Install Date - Lead Time. Required Submit = Install Date - (Lead + Review + Prep). Orange rows need a human decision (see Review Queue).
A4: Sub # | B4: Rev | C4: Description | D4: Spec Section | E4: Section Title | F4: Type | G4: Spec Ref | H4: Install Date | I4: Lead Time (wk) | J4: Review (wk) | K4: Prep (wk) | L4: Required Approval | M4: Required Submit | N4: Actual Submit | O4: Approval Date | P4: Status | Q4: Days to Due | R4: Origin | S4: Notes | T4: Spec Text
A5: 012100.01 | B5: 0 | C5: Submit proposals for purchase of products or systems included in allowances in the form specified for Change Orders. | D5: 01 21 00 | E5: Allowances | F5: REPORT | G5: 1.4.A p.18 | J5: ='Project Rules'!$B$5 | K5: ='Project Rules'!$B$6 | L5: =IF(OR(H5="",I5=""),"",H5-7*I5) | M5: =IF(OR(H5="",I5=""),"",H5-7*(I5+J5+K5)) | P5: Not Started | Q5: =IF(OR(M5="",P5="Approved",P5="Approved as Noted"),"",M5-TODAY()) | R5: Spec article | T5: Submit proposals for purchase of products or systems included in allowances in the form specified for Change Orders.
A6: 012100.02 | B6: 0 | C6: Invoices or delivery slips showing actual quantities of allowance materials delivered | D6: 01 21 00 | E6: Allowances | F6: REPORT | G6: 1.5.A p.18 | J6: ='Project Rules'!$B$5 | K6: ='Project Rules'!$B$6 | L6: =IF(OR(H6="",I6=""),"",H6-7*I6) | M6: =IF(OR(H6="",I6=""),"",H6-7*(I6+J6+K6)) | P6: Not Started | Q6: =IF(OR(M6="",P6="Approved",P6="Approved as Noted"),"",M6-TODAY()) | R6: Spec article | T6: Submit invoices or delivery slips to show actual quantities of materials delivered to the site for use in fulfillment of each allowance.
A7: 012100.03 | B7: 0 | C7: Time sheets and documentation of labor time and cost for allowance installation | D7: 01 21 00 | E7: Allowances | F7: REPORT | G7: 1.5.B p.18 | J7: ='Project Rules'!$B$5 | K7: ='Project Rules'!$B$6 | L7: =IF(OR(H7="",I7=""),"",H7-7*I7) | M7: =IF(OR(H7="",I7=""),"",H7-7*(I7+J7+K7)) | P7: Not Started | Q7: =IF(OR(M7="",P7="Approved",P7="Approved as Noted"),"",M7-TODAY()) | R7: Spec article | T7: Submit time sheets and other documentation to show labor time and cost for installation of allowance items that include installation as part of the allowance.
A8: 012900.01 | B8: 0 | C8: Schedule of values (AIA G703 format, one line per spec section) | D8: 01 29 00 | E8: Payment Procedures | F8: SCHED | G8: 1.3.A.2 p.28 | J8: ='Project Rules'!$B$5 | K8: ='Project Rules'!$B$6 | L8: =IF(OR(H8="",I8=""),"",H8-7*I8) | M8: =IF(OR(H8="",I8=""),"",H8-7*(I8+J8+K8)) | P8: Not Started | Q8: =IF(OR(M8="",P8="Approved",P8="Approved as Noted"),"",M8-TODAY()) | R8: Added by Claude | S8: Due 7 days before the first Application for Payment | T8: Submit the schedule of values to Architect at earliest possible date, but no later than seven days before the date scheduled for submittal of initial Applications for Payment.
A9: 012900.02 | B9: 0 | C9: Draft Application for Payment (7 days before due date) | D9: 01 29 00 | E9: Payment Procedures | F9: REPORT | G9: 1.4.A.1 p.28 | J9: ='Project Rules'!$B$5 | K9: ='Project Rules'!$B$6 | L9: =IF(OR(H9="",I9=""),"",H9-7*I9) | M9: =IF(OR(H9="",I9=""),"",H9-7*(I9+J9+K9)) | P9: Not Started | Q9: =IF(OR(M9="",P9="Approved",P9="Approved as Noted"),"",M9-TODAY()) | R9: Added by Claude | S9: Recurring, monthly | T9: Submit draft copy of Application for Payment seven days prior to due date for review by Architect.
A10: 012900.03 | B10: 0 | C10: Applications for Payment (three signed and notarized PDF copies, by email) | D10: 01 29 00 | E10: Payment Procedures | F10: REPORT | G10: 1.4.F p.29 | J10: ='Project Rules'!$B$5 | K10: ='Project Rules'!$B$6 | L10: =IF(OR(H10="",I10=""),"",H10-7*I10) | M10: =IF(OR(H10="",I10=""),"",H10-7*(I10+J10+K10)) | P10: Not Started | Q10: =IF(OR(M10="",P10="Approved",P10="Approved as Noted"),"",M10-TODAY()) | R10: Added by Claude | S10: Recurring, monthly | T10: Submit three signed and notarized PDF copies of each Application for Payment to Architect by email.
A11: 012900.04 | B11: 0 | C11: Waivers of mechanic's lien (partial with each application, conditional final at completion) | D11: 01 29 00 | E11: Payment Procedures | F11: CERT | G11: 1.4.G p.29 | J11: ='Project Rules'!$B$5 | K11: ='Project Rules'!$B$6 | L11: =IF(OR(H11="",I11=""),"",H11-7*I11) | M11: =IF(OR(H11="",I11=""),"",H11-7*(I11+J11+K11)) | P11: Not Started | Q11: =IF(OR(M11="",P11="Approved",P11="Approved as Noted"),"",M11-TODAY()) | R11: Added by Claude | S11: Recurring, with every Application for Payment | T11: With each Application for Payment, submit waivers of mechanic's lien from entities lawfully entitled to file a lien.
A12: 012900.05 | B12: 0 | C12: Initial Application for Payment package: subcontractor list, products list, staff and consultant lists | D12: 01 29 00 | E12: Payment Procedures | F12: REPORT | G12: 1.4.H p.28 | J12: ='Project Rules'!$B$5 | K12: ='Project Rules'!$B$6 | L12: =IF(OR(H12="",I12=""),"",H12-7*I12) | M12: =IF(OR(H12="",I12=""),"",H12-7*(I12+J12+K12)) | P12: Not Started | Q12: =IF(OR(M12="",P12="Approved",P12="Approved as Noted"),"",M12-TODAY()) | R12: Added by Claude | S12: Due with the first Application for Payment | T12: Initial Application for Payment: list of subcontractors, schedule of values, Contractor's construction schedule, products list, submittal schedule, list of staff assignments, list of principal consultants.
A13: 012900.06 | B13: 0 | C13: Building permits, authorizations and licenses from authorities having jurisdiction | D13: 01 29 00 | E13: Payment Procedures | F13: CERT | G13: 1.4.H.8-9 p.29 | J13: ='Project Rules'!$B$5 | K13: ='Project Rules'!$B$6 | L13: =IF(OR(H13="",I13=""),"",H13-7*I13) | M13: =IF(OR(H13="",I13=""),"",H13-7*(I13+J13+K13)) | P13: Not Started | Q13: =IF(OR(M13="",P13="Approved",P13="Approved as Noted"),"",M13-TODAY()) | R13: Added by Claude | S13: Due with the first Application for Payment | T13: Initial Application for Payment: copies of building permits; copies of authorizations and licenses from authorities having jurisdiction.
A14: 013100.01 | B14: 0 | C14: Subcontract List: Prepare a written summary identifying individuals or firms proposed for each portion of the Work, including those who are to furnish products or... | D14: 01 31 00 | E14: Project Management And Coordination | F14: REPORT | G14: 1.3.A p.31 | J14: ='Project Rules'!$B$5 | K14: ='Project Rules'!$B$6 | L14: =IF(OR(H14="",I14=""),"",H14-7*I14) | M14: =IF(OR(H14="",I14=""),"",H14-7*(I14+J14+K14)) | P14: Not Started | Q14: =IF(OR(M14="",P14="Approved",P14="Approved as Noted"),"",M14-TODAY()) | R14: Spec article | T14: Subcontract List: Prepare a written summary identifying individuals or firms proposed for each portion of the Work, including those who are to furnish products or equipment fabricated to a special design. Include the following information in tabular form: 1. Name, address, telephone number, and email address of entity performing subcontract or supplying products. 2. Number and title of related Specification Section(s) covered by subcontract. 3. Drawing number and detail references, as appropriate, covered by subcontract.
A15: 013100.02 | B15: 0 | C15: Key Personnel Names: 15 days prior to starting construction operations, submit a list of key personnel assignments, including superintendent and other personnel in... | D15: 01 31 00 | E15: Project Management And Coordination | F15: REPORT | G15: 1.3.B p.31 | J15: ='Project Rules'!$B$5 | K15: ='Project Rules'!$B$6 | L15: =IF(OR(H15="",I15=""),"",H15-7*I15) | M15: =IF(OR(H15="",I15=""),"",H15-7*(I15+J15+K15)) | P15: Not Started | Q15: =IF(OR(M15="",P15="Approved",P15="Approved as Noted"),"",M15-TODAY()) | R15: Spec article | T15: Key Personnel Names: 15 days prior to starting construction operations, submit a list of key personnel assignments, including superintendent and other personnel in attendance at Project site. Identify individuals and their duties and responsibilities; list addresses, cellular telephone numbers, and e-mail addresses. Provide names, addresses, and telephone numbers of individuals assigned as alternates in the absence of individuals assigned to Project. 1. Post copies of list in Project meeting room, in temporary field office, in web-based Project software directory, and in prominent location in built facility. Keep list current at all times.
A16: 013200.01 | B16: 0 | C16: Construction schedule files: working electronic copy and PDF | D16: 01 32 00 | E16: Construction Progress Documentation | F16: SCHED | G16: 1.3.A.1 p.38 | J16: ='Project Rules'!$B$5 | K16: ='Project Rules'!$B$6 | L16: =IF(OR(H16="",I16=""),"",H16-7*I16) | M16: =IF(OR(H16="",I16=""),"",H16-7*(I16+J16+K16)) | P16: Not Started | Q16: =IF(OR(M16="",P16="Approved",P16="Approved as Noted"),"",M16-TODAY()) | R16: Spec article | T16: Working electronic copy of schedule file.
A17: 013200.02 | B17: 0 | C17: Startup Network Diagram: Of size required to display entire network for entire construction period. | D17: 01 32 00 | E17: Construction Progress Documentation | F17: SCHED | G17: 1.3.B p.38 | J17: ='Project Rules'!$B$5 | K17: ='Project Rules'!$B$6 | L17: =IF(OR(H17="",I17=""),"",H17-7*I17) | M17: =IF(OR(H17="",I17=""),"",H17-7*(I17+J17+K17)) | P17: Not Started | Q17: =IF(OR(M17="",P17="Approved",P17="Approved as Noted"),"",M17-TODAY()) | R17: Spec article | T17: Startup Network Diagram: Of size required to display entire network for entire construction period. Show logic ties for activities.
A18: 013200.03 | B18: 0 | C18: Contractor's Construction Schedule: Initial schedule, of size required to display entire schedule for entire construction period. | D18: 01 32 00 | E18: Construction Progress Documentation | F18: SCHED | G18: 1.3.C p.38 | J18: ='Project Rules'!$B$5 | K18: ='Project Rules'!$B$6 | L18: =IF(OR(H18="",I18=""),"",H18-7*I18) | M18: =IF(OR(H18="",I18=""),"",H18-7*(I18+J18+K18)) | P18: Not Started | Q18: =IF(OR(M18="",P18="Approved",P18="Approved as Noted"),"",M18-TODAY()) | R18: Spec article | T18: Contractor's Construction Schedule: Initial schedule, of size required to display entire schedule for entire construction period.
A19: 013233.01 | B19: 0 | C19: Key Plan: Submit key plan of Project site and building with notation of vantage points marked for location and direction of each photograph and video recording. | D19: 01 32 33 | E19: Photographic Documentation | F19: REPORT | G19: 1.2.A p.45 | J19: ='Project Rules'!$B$5 | K19: ='Project Rules'!$B$6 | L19: =IF(OR(H19="",I19=""),"",H19-7*I19) | M19: =IF(OR(H19="",I19=""),"",H19-7*(I19+J19+K19)) | P19: Not Started | Q19: =IF(OR(M19="",P19="Approved",P19="Approved as Noted"),"",M19-TODAY()) | R19: Spec article | T19: Key Plan: Submit key plan of Project site and building with notation of vantage points marked for location and direction of each photograph and video recording. Indicate elevation or story of construction. Include same information as corresponding photographic documentation.
A20: 013233.02 | B20: 0 | C20: Digital Photographs: Submit image files within three days of taking photographs. | D20: 01 32 33 | E20: Photographic Documentation | F20: REPORT | G20: 1.2.B p.45 | J20: ='Project Rules'!$B$5 | K20: ='Project Rules'!$B$6 | L20: =IF(OR(H20="",I20=""),"",H20-7*I20) | M20: =IF(OR(H20="",I20=""),"",H20-7*(I20+J20+K20)) | P20: Not Started | Q20: =IF(OR(M20="",P20="Approved",P20="Approved as Noted"),"",M20-TODAY()) | R20: Spec article | T20: Digital Photographs: Submit image files within three days of taking photographs. 1. Submit photos by uploading to web-based Project management software site. Include copy of key plan indicating each photograph's location and direction. 2. Identification: Provide the following information with each image description in file metadata tag: a. Name of Project. b. Name and contact information for photographer. c. Name of Architect. d. Name of Contractor. e. Date photograph was taken. f. Description of location, vantage point, and direction. g. Unique sequential identifier keyed to accompanying key plan.
A21: 013233.03 | B21: 0 | C21: Submit video recordings by uploading to web-based Project management software site. | D21: 01 32 33 | E21: Photographic Documentation | F21: REPORT | G21: 1.2.C.1 p.45 | J21: ='Project Rules'!$B$5 | K21: ='Project Rules'!$B$6 | L21: =IF(OR(H21="",I21=""),"",H21-7*I21) | M21: =IF(OR(H21="",I21=""),"",H21-7*(I21+J21+K21)) | P21: Not Started | Q21: =IF(OR(M21="",P21="Approved",P21="Approved as Noted"),"",M21-TODAY()) | R21: Spec article | T21: Submit video recordings by uploading to web-based Project management software site. Include copy of key plan indicating each video's location and direction.
A22: 013233.04 | B22: 0 | C22: Photographer Qualifications: An individual who has been regularly engaged as a professional photographer of construction projects for not less than three years. | D22: 01 32 33 | E22: Photographic Documentation | F22: REPORT+CERT | G22: 1.2.D p.45 | J22: ='Project Rules'!$B$5 | K22: ='Project Rules'!$B$6 | L22: =IF(OR(H22="",I22=""),"",H22-7*I22) | M22: =IF(OR(H22="",I22=""),"",H22-7*(I22+J22+K22)) | P22: Not Started | Q22: =IF(OR(M22="",P22="Approved",P22="Approved as Noted"),"",M22-TODAY()) | R22: Spec article | T22: Photographer Qualifications: An individual who has been regularly engaged as a professional photographer of construction projects for not less than three years.
A23: 013300.01 | B23: 0 | C23: Submittal schedule: initial (first 60 days, long-lead items) and final | D23: 01 33 00 | E23: Submittal Procedures | F23: SCHED | G23: 1.3.A p.48 | J23: ='Project Rules'!$B$5 | K23: ='Project Rules'!$B$6 | L23: =IF(OR(H23="",I23=""),"",H23-7*I23) | M23: =IF(OR(H23="",I23=""),"",H23-7*(I23+J23+K23)) | P23: Not Started | Q23: =IF(OR(M23="",P23="Approved",P23="Approved as Noted"),"",M23-TODAY()) | R23: Added by Claude | S23: Initial with startup schedule; final with first complete construction schedule | T23: Submit, as an action submittal, a list of submittals in chronological order. Initial schedule with the startup construction schedule; final schedule with the first complete construction schedule.
A24: 013300.02 | B24: 0 | C24: Delegated-design services certification, signed and sealed by the design professional | D24: 01 33 00 | E24: Submittal Procedures | F24: CERT | G24: 1.7.B p.52 | J24: ='Project Rules'!$B$5 | K24: ='Project Rules'!$B$6 | L24: =IF(OR(H24="",I24=""),"",H24-7*I24) | M24: =IF(OR(H24="",I24=""),"",H24-7*(I24+J24+K24)) | P24: Not Started | Q24: =IF(OR(M24="",P24="Approved",P24="Approved as Noted"),"",M24-TODAY()) | R24: Added by Claude | S24: Only for products assigned as delegated design | T24: Submit digitally signed PDF certificate, signed and sealed by the responsible design professional, for each product and system assigned to the Contractor to design or certify.
A25: 013513.01 | B25: 0 | C25: Noise schedule: demolition and noisy operations with dates, times and duration | D25: 01 35 13 | E25: Hospital Project Procedures | F25: SCHED | G25: 1.4.A.3 p.54 | J25: ='Project Rules'!$B$5 | K25: ='Project Rules'!$B$6 | L25: =IF(OR(H25="",I25=""),"",H25-7*I25) | M25: =IF(OR(H25="",I25=""),"",H25-7*(I25+J25+K25)) | P25: Not Started | Q25: =IF(OR(M25="",P25="Approved",P25="Approved as Noted"),"",M25-TODAY()) | R25: Added by Claude | S25: As soon as practicable | T25: Submit "Noise Schedule" as soon as practicable indicating type of demolition and other noise inducing construction operations showing dates, times, and duration of such work.
A26: 013516.01 | B26: 0 | C26: Submit alteration work subschedule within seven days of date established for commencement of alteration work. | D26: 01 35 16 | E26: Alteration Project Procedures | F26: SCHED | G26: 1.5.A.1 p.59 | J26: ='Project Rules'!$B$5 | K26: ='Project Rules'!$B$6 | L26: =IF(OR(H26="",I26=""),"",H26-7*I26) | M26: =IF(OR(H26="",I26=""),"",H26-7*(I26+J26+K26)) | P26: Not Started | Q26: =IF(OR(M26="",P26="Approved",P26="Approved as Noted"),"",M26-TODAY()) | R26: Spec article | T26: Submit alteration work subschedule within seven days of date established for commencement of alteration work.
A27: 013516.02 | B27: 0 | C27: Preconstruction Documentation: Show preexisting conditions of adjoining construction and site improvements that are to remain, including finish surfaces, that might be... | D27: 01 35 16 | E27: Alteration Project Procedures | F27: REPORT | G27: 1.5.B p.59 | J27: ='Project Rules'!$B$5 | K27: ='Project Rules'!$B$6 | L27: =IF(OR(H27="",I27=""),"",H27-7*I27) | M27: =IF(OR(H27="",I27=""),"",H27-7*(I27+J27+K27)) | P27: Not Started | Q27: =IF(OR(M27="",P27="Approved",P27="Approved as Noted"),"",M27-TODAY()) | R27: Spec article | T27: Preconstruction Documentation: Show preexisting conditions of adjoining construction and site improvements that are to remain, including finish surfaces, that might be misconstrued as damage caused by Contractor's alteration work operations.
A28: 013516.03 | B28: 0 | C28: Alteration Work Program: Submit 30 days before work begins. | D28: 01 35 16 | E28: Alteration Project Procedures | F28: REPORT | G28: 1.5.C p.59 | J28: ='Project Rules'!$B$5 | K28: ='Project Rules'!$B$6 | L28: =IF(OR(H28="",I28=""),"",H28-7*I28) | M28: =IF(OR(H28="",I28=""),"",H28-7*(I28+J28+K28)) | P28: Not Started | Q28: =IF(OR(M28="",P28="Approved",P28="Approved as Noted"),"",M28-TODAY()) | R28: Spec article | T28: Alteration Work Program: Submit 30 days before work begins.
A29: 013516.04 | B29: 0 | C29: Fire-Prevention Plan: Submit 30 days before work begins. | D29: 01 35 16 | E29: Alteration Project Procedures | F29: REPORT | G29: 1.5.D p.59 | J29: ='Project Rules'!$B$5 | K29: ='Project Rules'!$B$6 | L29: =IF(OR(H29="",I29=""),"",H29-7*I29) | M29: =IF(OR(H29="",I29=""),"",H29-7*(I29+J29+K29)) | P29: Not Started | Q29: =IF(OR(M29="",P29="Approved",P29="Approved as Noted"),"",M29-TODAY()) | R29: Spec article | T29: Fire-Prevention Plan: Submit 30 days before work begins.
A30: 014000.01 | B30: 0 | C30: Mockup shop drawings: plans, sections, elevations, details, components and axonometrics | D30: 01 40 00 | E30: Quality Requirements | F30: SD | G30: 1.5.A p.64 | J30: ='Project Rules'!$B$5 | K30: ='Project Rules'!$B$6 | L30: =IF(OR(H30="",I30=""),"",H30-7*I30) | M30: =IF(OR(H30="",I30=""),"",H30-7*(I30+J30+K30)) | P30: Not Started | Q30: =IF(OR(M30="",P30="Approved",P30="Approved as Noted"),"",M30-TODAY()) | R30: Spec article (merged) | S30: Only for mockups the sections require | T30: Include plans, sections, elevations, and details, indicating materials and size of mockup construction. Indicate manufacturer and model number of individual components. Provide axonometric drawings for conditions difficult to illustrate in two dimensions.
A31: 014000.02 | B31: 0 | C31: Contractor's Quality-Control Plan: For quality-assurance and quality-control activities and responsibilities. | D31: 01 40 00 | E31: Quality Requirements | F31: REPORT | G31: 1.6.A p.64 | J31: ='Project Rules'!$B$5 | K31: ='Project Rules'!$B$6 | L31: =IF(OR(H31="",I31=""),"",H31-7*I31) | M31: =IF(OR(H31="",I31=""),"",H31-7*(I31+J31+K31)) | P31: Not Started | Q31: =IF(OR(M31="",P31="Approved",P31="Approved as Noted"),"",M31-TODAY()) | R31: Spec article | T31: Contractor's Quality-Control Plan: For quality-assurance and quality-control activities and responsibilities.
A32: 014000.03 | B32: 0 | C32: Qualification Data: For Contractor's quality-control personnel. | D32: 01 40 00 | E32: Quality Requirements | F32: CERT | G32: 1.6.B p.64 | J32: ='Project Rules'!$B$5 | K32: ='Project Rules'!$B$6 | L32: =IF(OR(H32="",I32=""),"",H32-7*I32) | M32: =IF(OR(H32="",I32=""),"",H32-7*(I32+J32+K32)) | P32: Not Started | Q32: =IF(OR(M32="",P32="Approved",P32="Approved as Noted"),"",M32-TODAY()) | R32: Spec article | T32: Qualification Data: For Contractor's quality-control personnel.
A33: 014000.04 | B33: 0 | C33: Contractor's Statement of Responsibility: When required by authorities having jurisdiction, submit copy of written statement of responsibility submitted to authorities... | D33: 01 40 00 | E33: Quality Requirements | F33: REPORT | G33: 1.6.C p.64 | J33: ='Project Rules'!$B$5 | K33: ='Project Rules'!$B$6 | L33: =IF(OR(H33="",I33=""),"",H33-7*I33) | M33: =IF(OR(H33="",I33=""),"",H33-7*(I33+J33+K33)) | P33: Not Started | Q33: =IF(OR(M33="",P33="Approved",P33="Approved as Noted"),"",M33-TODAY()) | R33: Spec article | T33: Contractor's Statement of Responsibility: When required by authorities having jurisdiction, submit copy of written statement of responsibility submitted to authorities having jurisdiction before starting work on the following systems: 1. Primary wind-force-resisting system or a wind-resisting component listed in the Statement of Special Inspections.
A34: 014000.05 | B34: 0 | C34: Testing Agency Qualifications: For testing agencies specified in "Quality Assurance" Article to demonstrate their capabilities and experience. | D34: 01 40 00 | E34: Quality Requirements | F34: CERT | G34: 1.6.D p.64 | J34: ='Project Rules'!$B$5 | K34: ='Project Rules'!$B$6 | L34: =IF(OR(H34="",I34=""),"",H34-7*I34) | M34: =IF(OR(H34="",I34=""),"",H34-7*(I34+J34+K34)) | P34: Not Started | Q34: =IF(OR(M34="",P34="Approved",P34="Approved as Noted"),"",M34-TODAY()) | R34: Spec article | T34: Testing Agency Qualifications: For testing agencies specified in "Quality Assurance" Article to demonstrate their capabilities and experience. Include proof of qualifications in the form of a recent report on the inspection of the testing agency by a recognized authority.
A35: 014000.06 | B35: 0 | C35: Schedule of Tests and Inspections: Prepare in tabular form and include the following: 1. | D35: 01 40 00 | E35: Quality Requirements | F35: SCHED | G35: 1.6.E p.64 | J35: ='Project Rules'!$B$5 | K35: ='Project Rules'!$B$6 | L35: =IF(OR(H35="",I35=""),"",H35-7*I35) | M35: =IF(OR(H35="",I35=""),"",H35-7*(I35+J35+K35)) | P35: Not Started | Q35: =IF(OR(M35="",P35="Approved",P35="Approved as Noted"),"",M35-TODAY()) | R35: Spec article | T35: Schedule of Tests and Inspections: Prepare in tabular form and include the following: 1. Specification Section number and title. 2. Entity responsible for performing tests and inspections. 3. Description of test and inspection.
A36: 015000.01 | B36: 0 | C36: Site Utilization Plan: Show temporary facilities, temporary utility lines and connections, staging areas, construction site entrances, vehicle circulation, and parking... | D36: 01 50 00 | E36: Temporary Facilities And Controls | F36: REPORT | G36: 1.3.A p.71 | J36: ='Project Rules'!$B$5 | K36: ='Project Rules'!$B$6 | L36: =IF(OR(H36="",I36=""),"",H36-7*I36) | M36: =IF(OR(H36="",I36=""),"",H36-7*(I36+J36+K36)) | P36: Not Started | Q36: =IF(OR(M36="",P36="Approved",P36="Approved as Noted"),"",M36-TODAY()) | R36: Spec article | T36: Site Utilization Plan: Show temporary facilities, temporary utility lines and connections, staging areas, construction site entrances, vehicle circulation, and parking areas for construction personnel.
A37: 015000.02 | B37: 0 | C37: Implementation and Termination Schedule: Within 15 days of date established for commencement of the Work, submit schedule indicating implementation and termination dates... | D37: 01 50 00 | E37: Temporary Facilities And Controls | F37: SCHED | G37: 1.3.B p.71 | J37: ='Project Rules'!$B$5 | K37: ='Project Rules'!$B$6 | L37: =IF(OR(H37="",I37=""),"",H37-7*I37) | M37: =IF(OR(H37="",I37=""),"",H37-7*(I37+J37+K37)) | P37: Not Started | Q37: =IF(OR(M37="",P37="Approved",P37="Approved as Noted"),"",M37-TODAY()) | R37: Spec article | T37: Implementation and Termination Schedule: Within 15 days of date established for commencement of the Work, submit schedule indicating implementation and termination dates of each temporary utility.
A38: 015000.03 | B38: 0 | C38: Project Identification and Temporary Signs: Show fabrication and installation details, including plans, elevations, details, layouts, typestyles, graphic elements, and... | D38: 01 50 00 | E38: Temporary Facilities And Controls | F38: REPORT | G38: 1.3.C p.71 | J38: ='Project Rules'!$B$5 | K38: ='Project Rules'!$B$6 | L38: =IF(OR(H38="",I38=""),"",H38-7*I38) | M38: =IF(OR(H38="",I38=""),"",H38-7*(I38+J38+K38)) | P38: Not Started | Q38: =IF(OR(M38="",P38="Approved",P38="Approved as Noted"),"",M38-TODAY()) | R38: Spec article | T38: Project Identification and Temporary Signs: Show fabrication and installation details, including plans, elevations, details, layouts, typestyles, graphic elements, and message content.
A39: 015000.04 | B39: 0 | C39: Fire-Safety Program: Show compliance with requirements of NFPA 241 and authorities having jurisdiction. | D39: 01 50 00 | E39: Temporary Facilities And Controls | F39: REPORT | G39: 1.3.D p.71 | J39: ='Project Rules'!$B$5 | K39: ='Project Rules'!$B$6 | L39: =IF(OR(H39="",I39=""),"",H39-7*I39) | M39: =IF(OR(H39="",I39=""),"",H39-7*(I39+J39+K39)) | P39: Not Started | Q39: =IF(OR(M39="",P39="Approved",P39="Approved as Noted"),"",M39-TODAY()) | R39: Spec article | T39: Fire-Safety Program: Show compliance with requirements of NFPA 241 and authorities having jurisdiction. Indicate Contractor personnel responsible for management of fire-prevention program.
A40: 015000.05 | B40: 0 | C40: Moisture- and Mold-Protection Plan: Describe procedures and controls for protecting materials and construction from water absorption and damage and mold. | D40: 01 50 00 | E40: Temporary Facilities And Controls | F40: REPORT | G40: 1.3.E p.71 | J40: ='Project Rules'!$B$5 | K40: ='Project Rules'!$B$6 | L40: =IF(OR(H40="",I40=""),"",H40-7*I40) | M40: =IF(OR(H40="",I40=""),"",H40-7*(I40+J40+K40)) | P40: Not Started | Q40: =IF(OR(M40="",P40="Approved",P40="Approved as Noted"),"",M40-TODAY()) | R40: Spec article | T40: Moisture- and Mold-Protection Plan: Describe procedures and controls for protecting materials and construction from water absorption and damage and mold. Describe delivery, handling, storage, installation, and protection provisions for materials subject to water absorption or water damage. 1. Indicate procedures for discarding water-damaged materials, protocols for mitigating water intrusion into completed Work, and requirements for replacing water-damaged Work. 2. Indicate sequencing of work that requires water, such as sprayed fire-resistive materials, plastering, and terrazzo grinding, and describe plans for dealing with water from these operations. Show procedures for verifying that wet construction has dried sufficiently to permit installation of finish materials. 3. Indicate methods to be used to avoid trapping water in finished work.
A41: 015000.06 | B41: 0 | C41: Dust- and HVAC-Control Plan: Submit coordination drawing and narrative that indicates the dust- and HVAC-control measures proposed for use, proposed locations, and... | D41: 01 50 00 | E41: Temporary Facilities And Controls | F41: REPORT+SD | G41: 1.3.F p.71 | J41: ='Project Rules'!$B$5 | K41: ='Project Rules'!$B$6 | L41: =IF(OR(H41="",I41=""),"",H41-7*I41) | M41: =IF(OR(H41="",I41=""),"",H41-7*(I41+J41+K41)) | P41: Not Started | Q41: =IF(OR(M41="",P41="Approved",P41="Approved as Noted"),"",M41-TODAY()) | R41: Spec article | T41: Dust- and HVAC-Control Plan: Submit coordination drawing and narrative that indicates the dust- and HVAC-control measures proposed for use, proposed locations, and proposed time frame for their operation. Include the following: 1. Locations of dust-control partitions at each phase of work. 2. HVAC system isolation schematic drawing. 3. Location of proposed air-filtration system discharge. 4. Waste-handling procedures. 5. Other dust-control measures.
A42: 015000.07 | B42: 0 | C42: Noise and Vibration Control Plan: Identify construction activities that may impact the occupancy and use of existing spaces within the building or adjacent existing... | D42: 01 50 00 | E42: Temporary Facilities And Controls | F42: REPORT | G42: 1.3.G p.71 | J42: ='Project Rules'!$B$5 | K42: ='Project Rules'!$B$6 | L42: =IF(OR(H42="",I42=""),"",H42-7*I42) | M42: =IF(OR(H42="",I42=""),"",H42-7*(I42+J42+K42)) | P42: Not Started | Q42: =IF(OR(M42="",P42="Approved",P42="Approved as Noted"),"",M42-TODAY()) | R42: Spec article | T42: Noise and Vibration Control Plan: Identify construction activities that may impact the occupancy and use of existing spaces within the building or adjacent existing buildings, whether occupied by others, or occupied by the Owner. Include the following: 1. Methods used to meet the goals and requirements of the Owner. 2. Concrete cutting method(s) to be used. 3. Location of construction devices on the site.
... A50: 017300.03 | B50: 0 | C50: Final Property Survey: Submit 10 copies showing the Work performed and record survey data. | D50: 01 73 00 | E50: Execution | F50: REPORT | G50: 1.5.A p.90 | J50: ='Project Rules'!$B$5 | K50: ='Project Rules'!$B$6 | L50: =IF(OR(H50="",I50=""),"",H50-7*I50) | M50: =IF(OR(H50="",I50=""),"",H50-7*(I50+J50+K50)) | P50: Not Started | Q50: =IF(OR(M50="",P50="Approved",P50="Approved as Noted"),"",M50-TODAY()) | R50: Spec article | T50: Final Property Survey: Submit 10 copies showing the Work performed and record survey data.
A51: 017700.01 | B51: 0 | C51: Project warranties assembled as one bookmarked PDF with table of contents | D51: 01 77 00 | E51: Closeout Procedures | F51: WARR | G51: 1.10.C p.98 | J51: ='Project Rules'!$B$5 | K51: ='Project Rules'!$B$6 | L51: =IF(OR(H51="",I51=""),"",H51-7*I51) | M51: =IF(OR(H51="",I51=""),"",H51-7*(I51+J51+K51)) | P51: Not Started | Q51: =IF(OR(M51="",P51="Approved",P51="Approved as Noted"),"",M51-TODAY()) | R51: Added by Claude | S51: Upload to project software; provide extra copies for O&M manuals | T51: Provide warranties and bonds in PDF format. Assemble complete warranty and bond submittal package into a single electronic PDF file with bookmarks.
A52: 017700.02 | B52: 0 | C52: Product Data: For each type of cleaning agent. | D52: 01 77 00 | E52: Closeout Procedures | F52: PD | G52: 1.3.A p.96 | J52: ='Project Rules'!$B$5 | K52: ='Project Rules'!$B$6 | L52: =IF(OR(H52="",I52=""),"",H52-7*I52) | M52: =IF(OR(H52="",I52=""),"",H52-7*(I52+J52+K52)) | P52: Not Started | Q52: =IF(OR(M52="",P52="Approved",P52="Approved as Noted"),"",M52-TODAY()) | R52: Spec article | T52: Product Data: For each type of cleaning agent.
A53: 017700.03 | B53: 0 | C53: Contractor's List of Incomplete Items: Initial submittal at Substantial Completion. | D53: 01 77 00 | E53: Closeout Procedures | F53: REPORT | G53: 1.3.B p.96 | J53: ='Project Rules'!$B$5 | K53: ='Project Rules'!$B$6 | L53: =IF(OR(H53="",I53=""),"",H53-7*I53) | M53: =IF(OR(H53="",I53=""),"",H53-7*(I53+J53+K53)) | P53: Not Started | Q53: =IF(OR(M53="",P53="Approved",P53="Approved as Noted"),"",M53-TODAY()) | R53: Spec article | T53: Contractor's List of Incomplete Items: Initial submittal at Substantial Completion.
A54: 017700.04 | B54: 0 | C54: Certified List of Incomplete Items: Final submittal at Final Completion. | D54: 01 77 00 | E54: Closeout Procedures | F54: REPORT | G54: 1.3.C p.96 | J54: ='Project Rules'!$B$5 | K54: ='Project Rules'!$B$6 | L54: =IF(OR(H54="",I54=""),"",H54-7*I54) | M54: =IF(OR(H54="",I54=""),"",H54-7*(I54+J54+K54)) | P54: Not Started | Q54: =IF(OR(M54="",P54="Approved",P54="Approved as Noted"),"",M54-TODAY()) | R54: Spec article | T54: Certified List of Incomplete Items: Final submittal at Final Completion.
A55: 017700.05 | B55: 0 | C55: Certificates of Release: From authorities having jurisdiction. | D55: 01 77 00 | E55: Closeout Procedures | F55: CERT | G55: 1.4.A p.96 | J55: ='Project Rules'!$B$5 | K55: ='Project Rules'!$B$6 | L55: =IF(OR(H55="",I55=""),"",H55-7*I55) | M55: =IF(OR(H55="",I55=""),"",H55-7*(I55+J55+K55)) | P55: Not Started | Q55: =IF(OR(M55="",P55="Approved",P55="Approved as Noted"),"",M55-TODAY()) | R55: Spec article | T55: Certificates of Release: From authorities having jurisdiction.
A56: 017700.06 | B56: 0 | C56: Certificate of Insurance: For continuing coverage. | D56: 01 77 00 | E56: Closeout Procedures | F56: CERT | G56: 1.4.B p.96 | J56: ='Project Rules'!$B$5 | K56: ='Project Rules'!$B$6 | L56: =IF(OR(H56="",I56=""),"",H56-7*I56) | M56: =IF(OR(H56="",I56=""),"",H56-7*(I56+J56+K56)) | P56: Not Started | Q56: =IF(OR(M56="",P56="Approved",P56="Approved as Noted"),"",M56-TODAY()) | R56: Spec article | T56: Certificate of Insurance: For continuing coverage.
A57: 017700.07 | B57: 0 | C57: Field Report: For pest-control inspection. | D57: 01 77 00 | E57: Closeout Procedures | F57: REPORT | G57: 1.4.C p.96 | J57: ='Project Rules'!$B$5 | K57: ='Project Rules'!$B$6 | L57: =IF(OR(H57="",I57=""),"",H57-7*I57) | M57: =IF(OR(H57="",I57=""),"",H57-7*(I57+J57+K57)) | P57: Not Started | Q57: =IF(OR(M57="",P57="Approved",P57="Approved as Noted"),"",M57-TODAY()) | R57: Spec article | T57: Field Report: For pest-control inspection.
A58: 017700.08 | B58: 0 | C58: Schedule of Maintenance Material Items: For maintenance material submittal items required by other Sections. | D58: 01 77 00 | E58: Closeout Procedures | F58: SCHED | G58: 1.5.A p.96 | J58: ='Project Rules'!$B$5 | K58: ='Project Rules'!$B$6 | L58: =IF(OR(H58="",I58=""),"",H58-7*I58) | M58: =IF(OR(H58="",I58=""),"",H58-7*(I58+J58+K58)) | P58: Not Started | Q58: =IF(OR(M58="",P58="Approved",P58="Approved as Noted"),"",M58-TODAY()) | R58: Spec article | T58: Schedule of Maintenance Material Items: For maintenance material submittal items required by other Sections.
A59: 017700.09 | B59: 0 | C59: Contractor's list of incomplete items (punch list) at Substantial Completion, with value of each item | D59: 01 77 00 | E59: Closeout Procedures | F59: REPORT | G59: 1.7.A p.96 | J59: ='Project Rules'!$B$5 | K59: ='Project Rules'!$B$6 | L59: =IF(OR(H59="",I59=""),"",H59-7*I59) | M59: =IF(OR(H59="",I59=""),"",H59-7*(I59+J59+K59)) | P59: Not Started | Q59: =IF(OR(M59="",P59="Approved",P59="Approved as Noted"),"",M59-TODAY()) | R59: Added by Claude | S59: At Substantial Completion | T59: Prepare and submit a list of items to be completed and corrected, indicating the value of each item and reasons why the Work is incomplete.
A60: 017700.10 | B60: 0 | C60: Closeout submittals before Substantial Completion: warranties, bonds, maintenance agreements, final certifications | D60: 01 77 00 | E60: Closeout Procedures | F60: WARR | G60: 1.7.B.3 p.97 | J60: ='Project Rules'!$B$5 | K60: ='Project Rules'!$B$6 | L60: =IF(OR(H60="",I60=""),"",H60-7*I60) | M60: =IF(OR(H60="",I60=""),"",H60-7*(I60+J60+K60)) | P60: Not Started | Q60: =IF(OR(M60="",P60="Approved",P60="Approved as Noted"),"",M60-TODAY()) | R60: Added by Claude | S60: Due 10 days before requesting Substantial Completion inspection | T60: Submit closeout submittals specified in individual Sections, including specific warranties, workmanship bonds, maintenance service agreements, final certifications, and similar documents.
A61: 017700.11 | B61: 0 | C61: Maintenance materials: tools, spare parts and extra materials delivered to Owner, with signed receipt | D61: 01 77 00 | E61: Closeout Procedures | F61: OM | G61: 1.7.B.4 p.97 | J61: ='Project Rules'!$B$5 | K61: ='Project Rules'!$B$6 | L61: =IF(OR(H61="",I61=""),"",H61-7*I61) | M61: =IF(OR(H61="",I61=""),"",H61-7*(I61+J61+K61)) | P61: Not Started | Q61: =IF(OR(M61="",P61="Approved",P61="Approved as Noted"),"",M61-TODAY()) | R61: Added by Claude | S61: Due 10 days before requesting Substantial Completion inspection | T61: Submit maintenance material submittals specified in individual Sections, including tools, spare parts, extra materials, and similar items, and deliver to location designated by Architect.
A62: 017700.12 | B62: 0 | C62: Testing, adjusting and balancing records | D62: 01 77 00 | E62: Closeout Procedures | F62: TEST | G62: 1.7.B.5 p.97 | J62: ='Project Rules'!$B$5 | K62: ='Project Rules'!$B$6 | L62: =IF(OR(H62="",I62=""),"",H62-7*I62) | M62: =IF(OR(H62="",I62=""),"",H62-7*(I62+J62+K62)) | P62: Not Started | Q62: =IF(OR(M62="",P62="Approved",P62="Approved as Noted"),"",M62-TODAY()) | R62: Added by Claude | S62: Due 10 days before requesting Substantial Completion inspection | T62: Submit testing, adjusting, and balancing records.
A63: 017700.13 | B63: 0 | C63: Changeover information for Owner's occupancy, use, operation and maintenance | D63: 01 77 00 | E63: Closeout Procedures | F63: REPORT | G63: 1.7.B.6 p.97 | J63: ='Project Rules'!$B$5 | K63: ='Project Rules'!$B$6 | L63: =IF(OR(H63="",I63=""),"",H63-7*I63) | M63: =IF(OR(H63="",I63=""),"",H63-7*(I63+J63+K63)) | P63: Not Started | Q63: =IF(OR(M63="",P63="Approved",P63="Approved as Noted"),"",M63-TODAY()) | R63: Added by Claude | S63: Due 10 days before requesting Substantial Completion inspection | T63: Submit changeover information related to Owner's occupancy, use, operation, and maintenance.
A64: 017700.14 | B64: 0 | C64: Written request for Substantial Completion inspection (10 days notice) | D64: 01 77 00 | E64: Closeout Procedures | F64: REPORT | G64: 1.7.D p.97 | J64: ='Project Rules'!$B$5 | K64: ='Project Rules'!$B$6 | L64: =IF(OR(H64="",I64=""),"",H64-7*I64) | M64: =IF(OR(H64="",I64=""),"",H64-7*(I64+J64+K64)) | P64: Not Started | Q64: =IF(OR(M64="",P64="Approved",P64="Approved as Noted"),"",M64-TODAY()) | R64: Added by Claude | S64: 10 days before inspection | T64: Submit a written request for inspection to determine Substantial Completion a minimum of 10 days prior.
A65: 017700.15 | B65: 0 | C65: Final Completion photographic documentation | D65: 01 77 00 | E65: Closeout Procedures | F65: REPORT | G65: 1.8.A.5 p.97 | J65: ='Project Rules'!$B$5 | K65: ='Project Rules'!$B$6 | L65: =IF(OR(H65="",I65=""),"",H65-7*I65) | M65: =IF(OR(H65="",I65=""),"",H65-7*(I65+J65+K65)) | P65: Not Started | Q65: =IF(OR(M65="",P65="Approved",P65="Approved as Noted"),"",M65-TODAY()) | R65: Added by Claude | S65: Before Final Completion inspection | T65: Submit Final Completion photographic documentation.
A66: 017700.16 | B66: 0 | C66: Written request for final inspection (10 days notice) | D66: 01 77 00 | E66: Closeout Procedures | F66: REPORT | G66: 1.8.B p.98 | J66: ='Project Rules'!$B$5 | K66: ='Project Rules'!$B$6 | L66: =IF(OR(H66="",I66=""),"",H66-7*I66) | M66: =IF(OR(H66="",I66=""),"",H66-7*(I66+J66+K66)) | P66: Not Started | Q66: =IF(OR(M66="",P66="Approved",P66="Approved as Noted"),"",M66-TODAY()) | R66: Added by Claude | S66: 10 days before final inspection | T66: Submit a written request for final inspection to determine acceptance a minimum of 10 days prior.
A67: 017823.01 | B67: 0 | C67: Submit operation and maintenance manuals indicated. | D67: 01 78 23 | E67: Operation And Maintenance Data | F67: OM | G67: 1.3.A p.100 | J67: ='Project Rules'!$B$5 | K67: ='Project Rules'!$B$6 | L67: =IF(OR(H67="",I67=""),"",H67-7*I67) | M67: =IF(OR(H67="",I67=""),"",H67-7*(I67+J67+K67)) | P67: Not Started | Q67: =IF(OR(M67="",P67="Approved",P67="Approved as Noted"),"",M67-TODAY()) | R67: Spec article | T67: Submit operation and maintenance manuals indicated. Provide content for each manual as specified in individual Specification Sections, and as reviewed and approved at the time of Section submittals. Submit reviewed manual content formatted and organized as required by this Section. 1. Architect will comment on whether content of operation and maintenance submittals is acceptable. 2. Where applicable, clarify and update reviewed manual content to correspond to revisions and field conditions.
A68: 017823.02 | B68: 0 | C68: O&M manuals: draft copy at least 30 days before demonstration and training | D68: 01 78 23 | E68: Operation And Maintenance Data | F68: OM | G68: 1.3.C p.100 | J68: ='Project Rules'!$B$5 | K68: ='Project Rules'!$B$6 | L68: =IF(OR(H68="",I68=""),"",H68-7*I68) | M68: =IF(OR(H68="",I68=""),"",H68-7*(I68+J68+K68)) | P68: Not Started | Q68: =IF(OR(M68="",P68="Approved",P68="Approved as Noted"),"",M68-TODAY()) | R68: Spec article | T68: Initial Manual Submittal: Submit draft copy of each manual at least 30 days before commencing demonstration and training. Architect will comment on whether general scope and content of manual are acceptable.
A69: 017823.03 | B69: 0 | C69: O&M manuals: final form before requesting inspection for Substantial Completion | D69: 01 78 23 | E69: Operation And Maintenance Data | F69: OM | G69: 1.3.D p.100 | J69: ='Project Rules'!$B$5 | K69: ='Project Rules'!$B$6 | L69: =IF(OR(H69="",I69=""),"",H69-7*I69) | M69: =IF(OR(H69="",I69=""),"",H69-7*(I69+J69+K69)) | P69: Not Started | Q69: =IF(OR(M69="",P69="Approved",P69="Approved as Noted"),"",M69-TODAY()) | R69: Spec article | T69: Final Manual Submittal: Submit each manual in final form prior to requesting inspection for Substantial Completion and at least 15 days before commencing demonstration and training. Architect will return copy with comments. 1. Correct or revise each manual to comply with Architect's comments. Submit copies of each corrected manual within 15 days of receipt of Architect's comments and prior to commencing demonstration and training.
A70: 017839.01 | B70: 0 | C70: Record drawings: marked-up record prints, initial and final submittals | D70: 01 78 39 | E70: Project Record Documents | F70: RECORD | G70: 1.2.A.1 p.105 | J70: ='Project Rules'!$B$5 | K70: ='Project Rules'!$B$6 | L70: =IF(OR(H70="",I70=""),"",H70-7*I70) | M70: =IF(OR(H70="",I70=""),"",H70-7*(I70+J70+K70)) | P70: Not Started | Q70: =IF(OR(M70="",P70="Approved",P70="Approved as Noted"),"",M70-TODAY()) | R70: Spec article | T70: Number of Copies: Submit one set(s) of marked-up record prints.
A71: 017839.02 | B71: 0 | C71: Record Specifications: Submit annotated PDF electronic files of Project's Specifications, including addenda and Contract modifications. | D71: 01 78 39 | E71: Project Record Documents | F71: RECORD | G71: 1.2.B p.105 | J71: ='Project Rules'!$B$5 | K71: ='Project Rules'!$B$6 | L71: =IF(OR(H71="",I71=""),"",H71-7*I71) | M71: =IF(OR(H71="",I71=""),"",H71-7*(I71+J71+K71)) | P71: Not Started | Q71: =IF(OR(M71="",P71="Approved",P71="Approved as Noted"),"",M71-TODAY()) | R71: Spec article | T71: Record Specifications: Submit annotated PDF electronic files of Project's Specifications, including addenda and Contract modifications.
A72: 017839.03 | B72: 0 | C72: Record Product Data: Submit annotated PDF electronic files and directories of each submittal. | D72: 01 78 39 | E72: Project Record Documents | F72: RECORD | G72: 1.2.C p.105 | J72: ='Project Rules'!$B$5 | K72: ='Project Rules'!$B$6 | L72: =IF(OR(H72="",I72=""),"",H72-7*I72) | M72: =IF(OR(H72="",I72=""),"",H72-7*(I72+J72+K72)) | P72: Not Started | Q72: =IF(OR(M72="",P72="Approved",P72="Approved as Noted"),"",M72-TODAY()) | R72: Spec article | T72: Record Product Data: Submit annotated PDF electronic files and directories of each submittal. 1. Where record Product Data are required as part of operation and maintenance manuals, submit duplicate marked-up Product Data as a component of manual.
A73: 017839.04 | B73: 0 | C73: Report of items incorporated into Project Record Documents | D73: 01 78 39 | E73: Project Record Documents | F73: RECORD | G73: 1.2.E p.105 | J73: ='Project Rules'!$B$5 | K73: ='Project Rules'!$B$6 | L73: =IF(OR(H73="",I73=""),"",H73-7*I73) | M73: =IF(OR(H73="",I73=""),"",H73-7*(I73+J73+K73)) | P73: Not Started | Q73: =IF(OR(M73="",P73="Approved",P73="Approved as Noted"),"",M73-TODAY()) | R73: Spec article | T73: Reports: Submit written report indicating items incorporated into Project Record Documents concurrent with progress of the Work, including revisions, concealed conditions, field changes, product selections, and other notations incorporated.
A74: 017900.01 | B74: 0 | C74: Instruction Program: Submit outline of instructional program for demonstration and training, including a list of training modules and a schedule of proposed dates,... | D74: 01 79 00 | E74: Demonstration And Training | F74: SCHED | G74: 1.2.A p.108 | J74: ='Project Rules'!$B$5 | K74: ='Project Rules'!$B$6 | L74: =IF(OR(H74="",I74=""),"",H74-7*I74) | M74: =IF(OR(H74="",I74=""),"",H74-7*(I74+J74+K74)) | P74: Not Started | Q74: =IF(OR(M74="",P74="Approved",P74="Approved as Noted"),"",M74-TODAY()) | R74: Spec article | T74: Instruction Program: Submit outline of instructional program for demonstration and training, including a list of training modules and a schedule of proposed dates, times, length of instruction time, and instructors' names for each training module. Include learning objective and outline for each training module. 1. Indicate proposed training modules using manufacturer-produced demonstration and training video recordings for systems, equipment, and products in lieu of video recording of live instructional module.
A75: 017900.02 | B75: 0 | C75: Attendance Record: For each training module, submit list of participants and length of instruction time. | D75: 01 79 00 | E75: Demonstration And Training | F75: RECORD | G75: 1.2.B p.108 | J75: ='Project Rules'!$B$5 | K75: ='Project Rules'!$B$6 | L75: =IF(OR(H75="",I75=""),"",H75-7*I75) | M75: =IF(OR(H75="",I75=""),"",H75-7*(I75+J75+K75)) | P75: Not Started | Q75: =IF(OR(M75="",P75="Approved",P75="Approved as Noted"),"",M75-TODAY()) | R75: Spec article | T75: Attendance Record: For each training module, submit list of participants and length of instruction time.
A76: 017900.03 | B76: 0 | C76: Evaluations: For each participant and for each training module, submit results and documentation of performance-based test. | D76: 01 79 00 | E76: Demonstration And Training | F76: RECORD | G76: 1.2.C p.108 | J76: ='Project Rules'!$B$5 | K76: ='Project Rules'!$B$6 | L76: =IF(OR(H76="",I76=""),"",H76-7*I76) | M76: =IF(OR(H76="",I76=""),"",H76-7*(I76+J76+K76)) | P76: Not Started | Q76: =IF(OR(M76="",P76="Approved",P76="Approved as Noted"),"",M76-TODAY()) | R76: Spec article | T76: Evaluations: For each participant and for each training module, submit results and documentation of performance-based test.
A77: 017900.04 | B77: 0 | C77: Demonstration and Training Video Recordings: Submit two copies within seven days of end of each training module. | D77: 01 79 00 | E77: Demonstration And Training | F77: REPORT | G77: 1.3.A p.108 | J77: ='Project Rules'!$B$5 | K77: ='Project Rules'!$B$6 | L77: =IF(OR(H77="",I77=""),"",H77-7*I77) | M77: =IF(OR(H77="",I77=""),"",H77-7*(I77+J77+K77)) | P77: Not Started | Q77: =IF(OR(M77="",P77="Approved",P77="Approved as Noted"),"",M77-TODAY()) | R77: Spec article | T77: Demonstration and Training Video Recordings: Submit two copies within seven days of end of each training module. 1. Identification: On each copy, provide an applied label with the following information: a. Name of Project. b. Name and address of videographer. c. Name of Architect. d. Name of Contractor. e. Date of video recording. 2. Transcript: Prepared and bound in format matching operation and maintenance manuals. Mark appropriate identification on front and spine of each binder. Include a cover sheet with same label information as the corresponding video recording. Include name of Project and date of video recording on each page. 3. At completion of training, submit complete training manual(s) for Owner's use prepared in same PDF file format required for operation and maintenance manuals specified in Section 017823 "Operation and Maintenance Data."
A78: 024121.01 | B78: 0 | C78: Work Plan Approval Request form for work outside the construction area (2 weeks in advance) | D78: 02 41 21 | E78: Work At Existing Facility | F78: REPORT | G78: 3.1.B.1 p.122 | J78: ='Project Rules'!$B$5 | K78: ='Project Rules'!$B$6 | L78: =IF(OR(H78="",I78=""),"",H78-7*I78) | M78: =IF(OR(H78="",I78=""),"",H78-7*(I78+J78+K78)) | P78: Not Started | Q78: =IF(OR(M78="",P78="Approved",P78="Approved as Noted"),"",M78-TODAY()) | R78: Added by Claude | S78: Recurring, each time; due 2 weeks before the work | T78: The Contractor shall submit a "Work Plan Approval Request" form for all work to be performed outside the designated construction area at least two (2) weeks in advance of the proposed portion of work.
A79: 024121.02 | B79: 0 | C79: Outage Request form (2 weeks in advance), with proposed plan for review | D79: 02 41 21 | E79: Work At Existing Facility | F79: REPORT | G79: 3.1.B.2-3 p.122 | J79: ='Project Rules'!$B$5 | K79: ='Project Rules'!$B$6 | L79: =IF(OR(H79="",I79=""),"",H79-7*I79) | M79: =IF(OR(H79="",I79=""),"",H79-7*(I79+J79+K79)) | P79: Not Started | Q79: =IF(OR(M79="",P79="Approved",P79="Approved as Noted"),"",M79-TODAY()) | R79: Added by Claude | S79: Recurring, each outage; due 2 weeks before the outage | T79: The Contractor shall submit an "Outage Request" form at least two (2) weeks in advance of the proposed outage, with a detailed plan for the affected work or system.
A80: 035416.01 | B80: 0 | C80: Product Data: For each type of product. | D80: 03 54 16 | E80: Hydraulic Cement Underlayment | F80: PD | G80: 1.2.A p.127 | J80: ='Project Rules'!$B$5 | K80: ='Project Rules'!$B$6 | L80: =IF(OR(H80="",I80=""),"",H80-7*I80) | M80: =IF(OR(H80="",I80=""),"",H80-7*(I80+J80+K80)) | P80: Not Started | Q80: =IF(OR(M80="",P80="Approved",P80="Approved as Noted"),"",M80-TODAY()) | R80: Spec article | T80: Product Data: For each type of product.
A81: 035416.02 | B81: 0 | C81: Shop Drawings: Include plans indicating substrates, locations, and average depths of underlayment based on survey of substrate conditions. | D81: 03 54 16 | E81: Hydraulic Cement Underlayment | F81: SD+REPORT | G81: 1.2.B p.127 | J81: ='Project Rules'!$B$5 | K81: ='Project Rules'!$B$6 | L81: =IF(OR(H81="",I81=""),"",H81-7*I81) | M81: =IF(OR(H81="",I81=""),"",H81-7*(I81+J81+K81)) | P81: Not Started | Q81: =IF(OR(M81="",P81="Approved",P81="Approved as Noted"),"",M81-TODAY()) | R81: Spec article | T81: Shop Drawings: Include plans indicating substrates, locations, and average depths of underlayment based on survey of substrate conditions.
A82: 054523.01 | B82: 0 | C82: Product Data: For each type of product indicated. | D82: 05 45 23 | E82: Healthcare Metal Supports | F82: PD | G82: 1.4.B p.129 | J82: ='Project Rules'!$B$5 | K82: ='Project Rules'!$B$6 | L82: =IF(OR(H82="",I82=""),"",H82-7*I82) | M82: =IF(OR(H82="",I82=""),"",H82-7*(I82+J82+K82)) | P82: Not Started | Q82: =IF(OR(M82="",P82="Approved",P82="Approved as Noted"),"",M82-TODAY()) | R82: Spec article | T82: Product Data: For each type of product indicated.
A83: 054523.02 | B83: 0 | C83: Shop Drawings: Indicate plan layout, typical elevations, details and anchoring methods. | D83: 05 45 23 | E83: Healthcare Metal Supports | F83: SD | G83: 1.4.C p.129 | J83: ='Project Rules'!$B$5 | K83: ='Project Rules'!$B$6 | L83: =IF(OR(H83="",I83=""),"",H83-7*I83) | M83: =IF(OR(H83="",I83=""),"",H83-7*(I83+J83+K83)) | P83: Not Started | Q83: =IF(OR(M83="",P83="Approved",P83="Approved as Noted"),"",M83-TODAY()) | R83: Spec article | T83: Shop Drawings: Indicate plan layout, typical elevations, details and anchoring methods.
A84: 054523.03 | B84: 0 | C84: Delegated Design Data: For installed dimension support systems indicated to comply with certain design loads and deflection limits, include structural analysis data... | D84: 05 45 23 | E84: Healthcare Metal Supports | F84: CALC+SD | G84: 1.5.A p.130 | J84: ='Project Rules'!$B$5 | K84: ='Project Rules'!$B$6 | L84: =IF(OR(H84="",I84=""),"",H84-7*I84) | M84: =IF(OR(H84="",I84=""),"",H84-7*(I84+J84+K84)) | P84: Not Started | Q84: =IF(OR(M84="",P84="Approved",P84="Approved as Noted"),"",M84-TODAY()) | R84: Spec article | T84: Delegated Design Data: For installed dimension support systems indicated to comply with certain design loads and deflection limits, include structural analysis data signed and sealed by the qualified professional structural engineer responsible for their preparation.
A85: 054523.04 | B85: 0 | C85: Certificates verifying AWS qualifications within previous 12 months for each welder employed for Work. | D85: 05 45 23 | E85: Healthcare Metal Supports | F85: CERT | G85: 1.5.B p.130 | J85: ='Project Rules'!$B$5 | K85: ='Project Rules'!$B$6 | L85: =IF(OR(H85="",I85=""),"",H85-7*I85) | M85: =IF(OR(H85="",I85=""),"",H85-7*(I85+J85+K85)) | P85: Not Started | Q85: =IF(OR(M85="",P85="Approved",P85="Approved as Noted"),"",M85-TODAY()) | R85: Spec article | T85: Certificates verifying AWS qualifications within previous 12 months for each welder employed for Work.
A86: 054523.05 | B86: 0 | C86: Certifications specified in Quality Assurance article. | D86: 05 45 23 | E86: Healthcare Metal Supports | F86: CERT | G86: 1.5.C p.130 | J86: ='Project Rules'!$B$5 | K86: ='Project Rules'!$B$6 | L86: =IF(OR(H86="",I86=""),"",H86-7*I86) | M86: =IF(OR(H86="",I86=""),"",H86-7*(I86+J86+K86)) | P86: Not Started | Q86: =IF(OR(M86="",P86="Approved",P86="Approved as Noted"),"",M86-TODAY()) | R86: Spec article | T86: Certifications specified in Quality Assurance article.
A87: 054523.06 | B87: 0 | C87: Qualification Data: For professional Engineer. | D87: 05 45 23 | E87: Healthcare Metal Supports | F87: CERT | G87: 1.5.D p.130 | J87: ='Project Rules'!$B$5 | K87: ='Project Rules'!$B$6 | L87: =IF(OR(H87="",I87=""),"",H87-7*I87) | M87: =IF(OR(H87="",I87=""),"",H87-7*(I87+J87+K87)) | P87: Not Started | Q87: =IF(OR(M87="",P87="Approved",P87="Approved as Noted"),"",M87-TODAY()) | R87: Spec article | T87: Qualification Data: For professional Engineer.
A88: 061053.01 | B88: 0 | C88: Product Data: For each type of process and factory-fabricated product. | D88: 06 10 53 | E88: Miscellaneous Rough Carpentry | F88: PD | G88: 1.3.A p.132 | J88: ='Project Rules'!$B$5 | K88: ='Project Rules'!$B$6 | L88: =IF(OR(H88="",I88=""),"",H88-7*I88) | M88: =IF(OR(H88="",I88=""),"",H88-7*(I88+J88+K88)) | P88: Not Started | Q88: =IF(OR(M88="",P88="Approved",P88="Approved as Noted"),"",M88-TODAY()) | R88: Spec article | T88: Product Data: For each type of process and factory-fabricated product. Indicate component materials and dimensions and include construction and application details. 1. Include data for wood-preservative treatment from chemical treatment manufacturer and certification by treating plant that treated materials comply with requirements. Indicate type of preservative used and net amount of preservative retained. 2. Include data for fire-retardant treatment from chemical treatment manufacturer and certification by treating plant that treated materials comply with requirements. Include physical properties of treated materials based on testing by a qualified independent testing agency. 3. For fire-retardant treatments, include physical properties of treated lumber both before and after exposure to elevated temperatures, based on testing by a qualified independent testing agency according to ASTM D5664. 4. For products receiving a waterborne treatment, include statement that moisture content of treated materials was reduced to levels specified before shipment to Project site.
A89: 061053.02 | B89: 0 | C89: Preservative-treated wood. | D89: 06 10 53 | E89: Miscellaneous Rough Carpentry | F89: TEST | G89: 1.4.A.1 p.132 | J89: ='Project Rules'!$B$5 | K89: ='Project Rules'!$B$6 | L89: =IF(OR(H89="",I89=""),"",H89-7*I89) | M89: =IF(OR(H89="",I89=""),"",H89-7*(I89+J89+K89)) | P89: Not Started | Q89: =IF(OR(M89="",P89="Approved",P89="Approved as Noted"),"",M89-TODAY()) | R89: Spec article | T89: Preservative-treated wood.
A90: 061053.03 | B90: 0 | C90: Fire-retardant-treated wood. | D90: 06 10 53 | E90: Miscellaneous Rough Carpentry | F90: TEST | G90: 1.4.A.2 p.132 | J90: ='Project Rules'!$B$5 | K90: ='Project Rules'!$B$6 | L90: =IF(OR(H90="",I90=""),"",H90-7*I90) | M90: =IF(OR(H90="",I90=""),"",H90-7*(I90+J90+K90)) | P90: Not Started | Q90: =IF(OR(M90="",P90="Approved",P90="Approved as Noted"),"",M90-TODAY()) | R90: Spec article | T90: Fire-retardant-treated wood.
A91: 064116.01 | B91: 0 | C91: Include data for fire-retardant treatment from chemical-treatment manufacturer and certification by treating plant that treated materials comply with requirements. | D91: 06 41 16 | E91: Plastic-Laminate-Clad Architectural Cabinets | F91: PD | G91: 1.4.A.1 p.136 | J91: ='Project Rules'!$B$5 | K91: ='Project Rules'!$B$6 | L91: =IF(OR(H91="",I91=""),"",H91-7*I91) | M91: =IF(OR(H91="",I91=""),"",H91-7*(I91+J91+K91)) | P91: Not Started | Q91: =IF(OR(M91="",P91="Approved",P91="Approved as Noted"),"",M91-TODAY()) | R91: Spec article | T91: Include data for fire-retardant treatment from chemical-treatment manufacturer and certification by treating plant that treated materials comply with requirements.
... A132: 095113.07 | B132: 0 | C132: Maintenance Data: For finishes to include in maintenance manuals. | D132: 09 51 13 | E132: Acoustical Panel Ceilings | F132: OM | G132: 1.4.A p.171 | J132: ='Project Rules'!$B$5 | K132: ='Project Rules'!$B$6 | L132: =IF(OR(H132="",I132=""),"",H132-7*I132) | M132: =IF(OR(H132="",I132=""),"",H132-7*(I132+J132+K132)) | P132: Not Started | Q132: =IF(OR(M132="",P132="Approved",P132="Approved as Noted"),"",M132-TODAY()) | R132: Spec article | T132: Maintenance Data: For finishes to include in maintenance manuals.
A133: 095113.08 | B133: 0 | C133: Extra materials: ceiling panels from the same product run | D133: 09 51 13 | E133: Acoustical Panel Ceilings | F133: REPORT | G133: 1.5.A p.171 | J133: ='Project Rules'!$B$5 | K133: ='Project Rules'!$B$6 | L133: =IF(OR(H133="",I133=""),"",H133-7*I133) | M133: =IF(OR(H133="",I133=""),"",H133-7*(I133+J133+K133)) | P133: Not Started | Q133: =IF(OR(M133="",P133="Approved",P133="Approved as Noted"),"",M133-TODAY()) | R133: Spec article | S133: Delivered to Owner, not a review submittal | T133: Furnish extra materials, from the same product run, that match products installed and that are packaged with protective covering for storage and identified with labels describing contents. 1. Acoustical Ceiling Units: Full-size panels equal to 2percent of quantity installed. 2. Suspension-System Components: Quantity of each exposed component equal to 2 percent of quantity installed. 3. Hold-Down Clips: Equal to 2percent of quantity installed.
A134: 096516.01 | B134: 0 | C134: Product Data: For each type of product. | D134: 09 65 16 | E134: Resilient Sheet Flooring | F134: PD | G134: 1.2.A p.176 | J134: ='Project Rules'!$B$5 | K134: ='Project Rules'!$B$6 | L134: =IF(OR(H134="",I134=""),"",H134-7*I134) | M134: =IF(OR(H134="",I134=""),"",H134-7*(I134+J134+K134)) | P134: Not Started | Q134: =IF(OR(M134="",P134="Approved",P134="Approved as Noted"),"",M134-TODAY()) | R134: Spec article | T134: Product Data: For each type of product.
A135: 096516.02 | B135: 0 | C135: Include sheet flooring layouts, locations of seams, edges, columns, doorways, enclosing partitions, built-in furniture, cabinets, and cutouts. | D135: 09 65 16 | E135: Resilient Sheet Flooring | F135: SD | G135: 1.2.B.1 p.176 | J135: ='Project Rules'!$B$5 | K135: ='Project Rules'!$B$6 | L135: =IF(OR(H135="",I135=""),"",H135-7*I135) | M135: =IF(OR(H135="",I135=""),"",H135-7*(I135+J135+K135)) | P135: Not Started | Q135: =IF(OR(M135="",P135="Approved",P135="Approved as Noted"),"",M135-TODAY()) | R135: Spec article | T135: Include sheet flooring layouts, locations of seams, edges, columns, doorways, enclosing partitions, built-in furniture, cabinets, and cutouts.
A136: 096516.03 | B136: 0 | C136: Show details of special patterns. | D136: 09 65 16 | E136: Resilient Sheet Flooring | F136: SD | G136: 1.2.B.2 p.176 | J136: ='Project Rules'!$B$5 | K136: ='Project Rules'!$B$6 | L136: =IF(OR(H136="",I136=""),"",H136-7*I136) | M136: =IF(OR(H136="",I136=""),"",H136-7*(I136+J136+K136)) | P136: Not Started | Q136: =IF(OR(M136="",P136="Approved",P136="Approved as Noted"),"",M136-TODAY()) | R136: Spec article | T136: Show details of special patterns.
A137: 096516.04 | B137: 0 | C137: Samples for Verification: For each type of resilient sheet flooring, in manufacturer's standard size, but not less than 6-by-9-inch (150-by-230-mm) sections of each... | D137: 09 65 16 | E137: Resilient Sheet Flooring | F137: SAM | G137: 1.2.C p.176 | J137: ='Project Rules'!$B$5 | K137: ='Project Rules'!$B$6 | L137: =IF(OR(H137="",I137=""),"",H137-7*I137) | M137: =IF(OR(H137="",I137=""),"",H137-7*(I137+J137+K137)) | P137: Not Started | Q137: =IF(OR(M137="",P137="Approved",P137="Approved as Noted"),"",M137-TODAY()) | R137: Spec article | T137: Samples for Verification: For each type of resilient sheet flooring, in manufacturer's standard size, but not less than 6-by-9-inch (150-by-230-mm) sections of each color, texture, and pattern required. 1. For heat-welding bead, manufacturer's standard-size Samples, but not less than 9 inches (230 mm) long, of each color required.
A138: 096516.05 | B138: 0 | C138: Product Schedule: For resilient sheet flooring. | D138: 09 65 16 | E138: Resilient Sheet Flooring | F138: SCHED | G138: 1.2.D p.176 | J138: ='Project Rules'!$B$5 | K138: ='Project Rules'!$B$6 | L138: =IF(OR(H138="",I138=""),"",H138-7*I138) | M138: =IF(OR(H138="",I138=""),"",H138-7*(I138+J138+K138)) | P138: Not Started | Q138: =IF(OR(M138="",P138="Approved",P138="Approved as Noted"),"",M138-TODAY()) | R138: Spec article | T138: Product Schedule: For resilient sheet flooring.
A139: 096516.06 | B139: 0 | C139: Qualification Data: For Installer. | D139: 09 65 16 | E139: Resilient Sheet Flooring | F139: CERT | G139: 1.3.A p.176 | J139: ='Project Rules'!$B$5 | K139: ='Project Rules'!$B$6 | L139: =IF(OR(H139="",I139=""),"",H139-7*I139) | M139: =IF(OR(H139="",I139=""),"",H139-7*(I139+J139+K139)) | P139: Not Started | Q139: =IF(OR(M139="",P139="Approved",P139="Approved as Noted"),"",M139-TODAY()) | R139: Spec article | T139: Qualification Data: For Installer.
A140: 096516.07 | B140: 0 | C140: Maintenance Data: For each type of resilient sheet flooring to include in maintenance manuals. | D140: 09 65 16 | E140: Resilient Sheet Flooring | F140: OM | G140: 1.4.A p.176 | J140: ='Project Rules'!$B$5 | K140: ='Project Rules'!$B$6 | L140: =IF(OR(H140="",I140=""),"",H140-7*I140) | M140: =IF(OR(H140="",I140=""),"",H140-7*(I140+J140+K140)) | P140: Not Started | Q140: =IF(OR(M140="",P140="Approved",P140="Approved as Noted"),"",M140-TODAY()) | R140: Spec article | T140: Maintenance Data: For each type of resilient sheet flooring to include in maintenance manuals.
A141: 096516.08 | B141: 0 | C141: Extra materials: flooring from the same product run | D141: 09 65 16 | E141: Resilient Sheet Flooring | F141: REPORT | G141: 1.5.A p.176 | J141: ='Project Rules'!$B$5 | K141: ='Project Rules'!$B$6 | L141: =IF(OR(H141="",I141=""),"",H141-7*I141) | M141: =IF(OR(H141="",I141=""),"",H141-7*(I141+J141+K141)) | P141: Not Started | Q141: =IF(OR(M141="",P141="Approved",P141="Approved as Noted"),"",M141-TODAY()) | R141: Spec article | S141: Delivered to Owner, not a review submittal | T141: Furnish extra materials, from the same product run, that match products installed and that are packaged with protective covering for storage and identified with labels describing contents. 1. Resilient Sheet Flooring: Furnish not less than 10 linear feet (3 linear m) for every 500 linear feet (150 linear m) or fraction thereof, in roll form and in full roll width for each type, color, and pattern of flooring installed.
A142: 098116.01 | B142: 0 | C142: Product Data: For each type of product indicated. | D142: 09 81 16 | E142: Acoustical Blanket Insulation | F142: PD | G142: 1.2.A p.180 | J142: ='Project Rules'!$B$5 | K142: ='Project Rules'!$B$6 | L142: =IF(OR(H142="",I142=""),"",H142-7*I142) | M142: =IF(OR(H142="",I142=""),"",H142-7*(I142+J142+K142)) | P142: Not Started | Q142: =IF(OR(M142="",P142="Approved",P142="Approved as Noted"),"",M142-TODAY()) | R142: Spec article | T142: Product Data: For each type of product indicated.
A143: 099123.01 | B143: 0 | C143: Product Data: For each type of product. | D143: 09 91 23 | E143: Interior Painting | F143: PD | G143: 1.3.A p.182 | J143: ='Project Rules'!$B$5 | K143: ='Project Rules'!$B$6 | L143: =IF(OR(H143="",I143=""),"",H143-7*I143) | M143: =IF(OR(H143="",I143=""),"",H143-7*(I143+J143+K143)) | P143: Not Started | Q143: =IF(OR(M143="",P143="Approved",P143="Approved as Noted"),"",M143-TODAY()) | R143: Spec article | T143: Product Data: For each type of product. Include preparation requirements and application instructions. 1. Indicate VOC content.
A144: 099123.02 | B144: 0 | C144: Samples for Verification: For each type of paint system and in each color and gloss of topcoat. | D144: 09 91 23 | E144: Interior Painting | F144: SAM | G144: 1.3.B p.182 | J144: ='Project Rules'!$B$5 | K144: ='Project Rules'!$B$6 | L144: =IF(OR(H144="",I144=""),"",H144-7*I144) | M144: =IF(OR(H144="",I144=""),"",H144-7*(I144+J144+K144)) | P144: Not Started | Q144: =IF(OR(M144="",P144="Approved",P144="Approved as Noted"),"",M144-TODAY()) | R144: Spec article | T144: Samples for Verification: For each type of paint system and in each color and gloss of topcoat. 1. Submit Samples on rigid backing, 8 inches (200 mm) square. 2. Apply coats on Samples in steps to show each coat required for system. 3. Label each coat of each Sample. 4. Label each Sample for location and application area.
A145: 099123.03 | B145: 0 | C145: Product List: Cross-reference to paint system and locations of application areas. | D145: 09 91 23 | E145: Interior Painting | F145: SCHED | G145: 1.3.C p.182 | J145: ='Project Rules'!$B$5 | K145: ='Project Rules'!$B$6 | L145: =IF(OR(H145="",I145=""),"",H145-7*I145) | M145: =IF(OR(H145="",I145=""),"",H145-7*(I145+J145+K145)) | P145: Not Started | Q145: =IF(OR(M145="",P145="Approved",P145="Approved as Noted"),"",M145-TODAY()) | R145: Spec article | T145: Product List: Cross-reference to paint system and locations of application areas. Use same designations indicated on Drawings and in schedules. Include color designations.
A146: 099123.04 | B146: 0 | C146: Extra materials: paint from the same production run | D146: 09 91 23 | E146: Interior Painting | F146: REPORT | G146: 1.4.A p.182 | J146: ='Project Rules'!$B$5 | K146: ='Project Rules'!$B$6 | L146: =IF(OR(H146="",I146=""),"",H146-7*I146) | M146: =IF(OR(H146="",I146=""),"",H146-7*(I146+J146+K146)) | P146: Not Started | Q146: =IF(OR(M146="",P146="Approved",P146="Approved as Noted"),"",M146-TODAY()) | R146: Spec article | S146: Delivered to Owner, not a review submittal | T146: Furnish extra materials, from the same product run, that match products installed and that are packaged with protective covering for storage and identified with labels describing contents. 1. Paint: 5 percent, but not less than 1 gal. (3.8 L) of each material and color applied.
A147: 101400.01 | B147: 0 | C147: Product Data: Include manufacturer's construction details relative to materials, dimensions of individual components, profiles, and finishes for each type of sign... | D147: 10 14 00 | E147: Signage | F147: PD | G147: 1.2.A p.187 | J147: ='Project Rules'!$B$5 | K147: ='Project Rules'!$B$6 | L147: =IF(OR(H147="",I147=""),"",H147-7*I147) | M147: =IF(OR(H147="",I147=""),"",H147-7*(I147+J147+K147)) | P147: Not Started | Q147: =IF(OR(M147="",P147="Approved",P147="Approved as Noted"),"",M147-TODAY()) | R147: Spec article | T147: Product Data: Include manufacturer's construction details relative to materials, dimensions of individual components, profiles, and finishes for each type of sign required.
A148: 101400.02 | B148: 0 | C148: Shop Drawings: Provide shop drawings for fabrication and erection of signs. | D148: 10 14 00 | E148: Signage | F148: SD | G148: 1.2.B p.187 | J148: ='Project Rules'!$B$5 | K148: ='Project Rules'!$B$6 | L148: =IF(OR(H148="",I148=""),"",H148-7*I148) | M148: =IF(OR(H148="",I148=""),"",H148-7*(I148+J148+K148)) | P148: Not Started | Q148: =IF(OR(M148="",P148="Approved",P148="Approved as Noted"),"",M148-TODAY()) | R148: Spec article | T148: Shop Drawings: Provide shop drawings for fabrication and erection of signs. Include plans, elevations, and large-scale sections of typical members and other components. Show anchors, accessories, layout, and installation details.
...

Sheet Project Rules
A1: Project Rules
A2: Yellow cells are inputs. The Register sheet reads the review and prep weeks from here.
A4: Project | B4: Radiology Room E.D. Vol B
A5: Default review time (weeks) | B5: 2.14
A6: Default prep time (weeks) | B6: 1
A7: Numbering format | B7: Specification Section number, a sequential alphanumeric identifier, and an alphanumeric suffix for each resubmittal (for example 092913.01, then 092913.01.A).
A8: Copies and format | B8: Submit as PDF uploaded to the web-based project management software, with a paper transmittal when required. Samples for verification: three sets (Architect keeps two). Shop drawings and design data: six copies plus one electronic copy where a section states a count. Action and informational submittals from the same section go in separate packages.
A9: Source of rules | B9: Section 01 33 00 Submittal Procedures (pages 48 to 53), Section 01 77 00 Closeout Procedures, Section 01 29 00 Payment Procedures
A11: Project-wide submittal requirements
A12: 1. | B12: Initial review is 15 days (about 2.1 weeks) from the Architect's receipt. Each resubmittal review is another 15 days. Where sequential review by consultants or the Owner is indicated, allow 21 days for the initial review.
A13: 2. | B13: No extension of Contract Time is allowed for submittals sent too late to be processed, including resubmittals.
A14: 3. | B14: Initial submittal schedule must cover the first 60 days of construction and any long-lead items, and goes in with the startup construction schedule. The final schedule goes in with the first complete construction schedule.
A15: 4. | B15: Submit all items for a section together unless the approved submittal schedule allows partial submittals. Submit product data before shop drawings, and before or with samples.
A16: 5. | B16: Indicate deviations from the Contract Documents on each submittal, and identify options that need the Architect's selection.
A17: 6. | B17: The Architect returns without review any submittal that is incomplete, not reviewed and approved by the Contractor, received from anyone but the Contractor, or not required by the Contract Documents.
A18: 7. | B18: Use only final action submittals marked with the Architect's approval notation for construction.
A19: 8. | B19: Closeout items are due at least 10 days before the Substantial Completion inspection request.
A20: 9. | B20: Substitution requests (Section 01 25 00) are contractor-initiated and are not in this register.
A21: 10. | B21: Fire protection piping and sprinkler shop drawings go to the local Fire Marshal and the Owner's insurance underwriter before the Architect.
A22: 11. | B22: Prep time of 1 week is an assumption, not a spec requirement.

Sheet Review Queue
A1: Review Queue
A2: Items the extraction could not place with confidence. Confirm each, then edit or delete its row on the Register sheet.
A4: Sub # | B4: Spec Section | C4: Section Title | D4: Spec Ref | E4: Type | F4: Why it needs review | G4: Spec text | H4: Decision
A5: 013300.02 | B5: 01 33 00 | C5: Submittal Procedures | D5: 1.7.B p.52 | E5: CERT | F5: Applies only where a section assigns design to the Contractor. Radiology Vol B has 05 45 23 (metal supports) and 09 22 16 (metal framing). Confirm others. | G5: Submit digitally signed PDF certificate, signed and sealed by the responsible design professional, for each product and system assigned to the Contractor to design or certify.
A6: 134900.04 | B6: 13 49 00 | C6: Radiation Protection | D6: 1.5.A p.198 | E6: CERT | F6: Text says flush wood door manufacturer under a radiation protection section. Probably a carry-over. Confirm. | G6: Qualification Data: For flush wood door manufacturer.
A7: 211100.01 | B7: 21 11 00 | C7: Fire Protection Piping | D7: 1.05.A-D p.222 | E7: SD+PD+CALC | F7: Review time for the Fire Marshal and insurance underwriter is not stated. Confirm lead time with the sprinkler contractor. | G7: Prior to submittal to Architect, submit shop drawings, product data, and hydraulic calculations to local Fire Marshal and Owner's Insurance. After approval from local Fire Marshal and Owner's Insurance Underwriter, submit shop drawings, product data, and hydraulic calculations to Architect (with Certificate of Approval from local Fire Marshal and Owner's Insurance Underwriter for approval in accordance with Division 01 and Section 21 0010. Indicate pipe materials used, jointing methods, supports, floor and wall penetration seals. Indicate valve data and ratings.
A8: 211300.01 | B8: 21 13 00 | C8: Automatic Sprinkler Systems | D8: 1.06.A-C p.224 | E8: SD+PD+CALC | F8: Review time for the Fire Marshal and insurance underwriter is not stated. Confirm lead time with the sprinkler contractor. | G8: Prior to submittal to Architect submit shop drawings, product data, and hydraulic calculations to local Fire Marshal and Owner's Insurance Underwriter. After approval from local Fire Marshal and Owner's Insurance Underwriter submit shop drawings, product data and hydraulic calculations to Architect (with Certificate of Approval from local Fire Marshal and Owner's Insurance Underwriter) for approval in accordance with Division 01 and Section 21 0010. Indicate hydraulic calculations, detailed pipe layout, hangers and supports, components and accessories.
A9: 220529.01 | B9: 22 05 29 | C9: Plumbing Supports And Anchors | D9: 1.03.A p.240 | E9: PD | F9: Reads as a cross-reference to Division 01. Likely a duplicate of 1.03.B. | G9: Submit product data as required under provisions of Division 01 and Section 22 0010.
A10: 260527.01 | B10: 26 05 27 | C10: Sealing Of Penetrations | D10: 1.02.A p.333 | E10: SAM | F10: Request-only item. Confirm whether to track it. | G10: Samples: Provide samples upon written request.
A11: 265113.03 | B11: 26 51 13 | C11: Lighting | D11: 1.02.C p.353 | E11: SAM | F11: Request-only item. Confirm whether to track it. | G11: If required by Architect, submit samples of lighting fixtures for approval.

Sheet By Section
A1: Submittals by Spec Section
A3: Spec Section | B3: Section Title | C3: Submittals | D3: Approved | E3: Open
A4: 01 21 00 | B4: Allowances | C4: =COUNTIF(Register!$D$5:$D$247,A4) | D4: =COUNTIFS(Register!$D$5:$D$247,A4,Register!$P$5:$P$247,"Approved")+COUNTIFS(Register!$D$5:$D$247,A4,Register!$P$5:$P$247,"Approved as Noted") | E4: =C4-D4
A5: 01 29 00 | B5: Payment Procedures | C5: =COUNTIF(Register!$D$5:$D$247,A5) | D5: =COUNTIFS(Register!$D$5:$D$247,A5,Register!$P$5:$P$247,"Approved")+COUNTIFS(Register!$D$5:$D$247,A5,Register!$P$5:$P$247,"Approved as Noted") | E5: =C5-D5
A6: 01 31 00 | B6: Project Management And Coordination | C6: =COUNTIF(Register!$D$5:$D$247,A6) | D6: =COUNTIFS(Register!$D$5:$D$247,A6,Register!$P$5:$P$247,"Approved")+COUNTIFS(Register!$D$5:$D$247,A6,Register!$P$5:$P$247,"Approved as Noted") | E6: =C6-D6
A7: 01 32 00 | B7: Construction Progress Documentation | C7: =COUNTIF(Register!$D$5:$D$247,A7) | D7: =COUNTIFS(Register!$D$5:$D$247,A7,Register!$P$5:$P$247,"Approved")+COUNTIFS(Register!$D$5:$D$247,A7,Register!$P$5:$P$247,"Approved as Noted") | E7: =C7-D7
A8: 01 32 33 | B8: Photographic Documentation | C8: =COUNTIF(Register!$D$5:$D$247,A8) | D8: =COUNTIFS(Register!$D$5:$D$247,A8,Register!$P$5:$P$247,"Approved")+COUNTIFS(Register!$D$5:$D$247,A8,Register!$P$5:$P$247,"Approved as Noted") | E8: =C8-D8
A9: 01 33 00 | B9: Submittal Procedures | C9: =COUNTIF(Register!$D$5:$D$247,A9) | D9: =COUNTIFS(Register!$D$5:$D$247,A9,Register!$P$5:$P$247,"Approved")+COUNTIFS(Register!$D$5:$D$247,A9,Register!$P$5:$P$247,"Approved as Noted") | E9: =C9-D9
A10: 01 35 13 | B10: Hospital Project Procedures | C10: =COUNTIF(Register!$D$5:$D$247,A10) | D10: =COUNTIFS(Register!$D$5:$D$247,A10,Register!$P$5:$P$247,"Approved")+COUNTIFS(Register!$D$5:$D$247,A10,Register!$P$5:$P$247,"Approved as Noted") | E10: =C10-D10
A11: 01 35 16 | B11: Alteration Project Procedures | C11: =COUNTIF(Register!$D$5:$D$247,A11) | D11: =COUNTIFS(Register!$D$5:$D$247,A11,Register!$P$5:$P$247,"Approved")+COUNTIFS(Register!$D$5:$D$247,A11,Register!$P$5:$P$247,"Approved as Noted") | E11: =C11-D11
A12: 01 40 00 | B12: Quality Requirements | C12: =COUNTIF(Register!$D$5:$D$247,A12) | D12: =COUNTIFS(Register!$D$5:$D$247,A12,Register!$P$5:$P$247,"Approved")+COUNTIFS(Register!$D$5:$D$247,A12,Register!$P$5:$P$247,"Approved as Noted") | E12: =C12-D12
A13: 01 50 00 | B13: Temporary Facilities And Controls | C13: =COUNTIF(Register!$D$5:$D$247,A13) | D13: =COUNTIFS(Register!$D$5:$D$247,A13,Register!$P$5:$P$247,"Approved")+COUNTIFS(Register!$D$5:$D$247,A13,Register!$P$5:$P$247,"Approved as Noted") | E13: =C13-D13
A14: 01 57 19 | B14: Temporary Environmental Controls | C14: =COUNTIF(Register!$D$5:$D$247,A14) | D14: =COUNTIFS(Register!$D$5:$D$247,A14,Register!$P$5:$P$247,"Approved")+COUNTIFS(Register!$D$5:$D$247,A14,Register!$P$5:$P$247,"Approved as Noted") | E14: =C14-D14
A15: 01 73 00 | B15: Execution | C15: =COUNTIF(Register!$D$5:$D$247,A15) | D15: =COUNTIFS(Register!$D$5:$D$247,A15,Register!$P$5:$P$247,"Approved")+COUNTIFS(Register!$D$5:$D$247,A15,Register!$P$5:$P$247,"Approved as Noted") | E15: =C15-D15
... A76: 27 05 28 | B76: Empty Conduit Systems | C76: =COUNTIF(Register!$D$5:$D$247,A76) | D76: =COUNTIFS(Register!$D$5:$D$247,A76,Register!$P$5:$P$247,"Approved")+COUNTIFS(Register!$D$5:$D$247,A76,Register!$P$5:$P$247,"Approved as Noted") | E76: =C76-D76
A77: Total | C77: =SUM(C4:C76) | D77: =SUM(D4:D76) | E77: =SUM(E4:E76)

Sheet Legend
A1: Legend
A3: Type code | B3: Meaning
A4: PD | B4: Product data
A5: SD | B5: Shop drawings
A6: WD | B6: Wiring diagrams
A7: SAM | B7: Samples
A8: CALC | B8: Calculations
A9: CERT | B9: Certificates, qualifications
A10: TEST | B10: Test and inspection reports
A11: WARR | B11: Warranties
A12: OM | B12: Operation and maintenance data
A13: MOCKUP | B13: Mock-ups
A14: RECORD | B14: Record drawings and as-builts
... A18: OTHER | B18: Not classified
A20: Cell colors
B21: Input: edit these
B22: Needs a human decision
B23: Blue text: typed number. Green text: value linked from Project Rules. Black: formula or text.
